polyscope_persistence/__init__.py
polyscope_persistence/wrapper.py
polyscope_persistence-0.0.8.dist-info/LICENSE
polyscope_persistence-0.0.8.dist-info/METADATA
polyscope_persistence-0.0.8.dist-info/WHEEL
polyscope_persistence-0.0.8.dist-info/entry_points.txt
polyscope_persistence-0.0.8.dist-info/top_level.txt
polyscope_persistence-0.0.8.dist-info/RECORD
