Metadata-Version: 2.1
Name: polyscope-persistence
Version: 0.0.8
Summary: UNKNOWN
Home-page: UNKNOWN
License: UNKNOWN
Platform: UNKNOWN
License-File: LICENSE
Requires-Dist: polyscope
